vin_qr/__init__.py
vin_qr-0.0.1.dist-info/LICENSE
vin_qr-0.0.1.dist-info/METADATA
vin_qr-0.0.1.dist-info/WHEEL
vin_qr-0.0.1.dist-info/entry_points.txt
vin_qr-0.0.1.dist-info/top_level.txt
vin_qr-0.0.1.dist-info/RECORD
