Metadata-Version: 2.1
Name: vin_qr
Version: 0.0.1
Summary: Utility that generates QR code from the VIN number
Home-page: https://gitlab.com/maksmikhalov/vin_qr.git
Author: Maks Mikhalov
Author-email: dn2tx.com@gmail.com
Classifier: Programming Language :: Python :: 3
Classifier: License :: OSI Approved :: MIT License
Classifier: Operating System :: OS Independent
License-File: LICENSE
Requires-Dist: pylibdmtx==0.1.10
Requires-Dist: pillow==10.4.0
